{
	"name": "StoreNiftyData",
	"properties": {
		"linkedServiceName": {
			"referenceName": "SQLDBConnection",
			"type": "LinkedServiceReference"
		},
		"annotations": [],
		"type": "AzureSqlTable",
		"schema": [
			{
				"name": "CompanyName",
				"type": "varchar"
			},
			{
				"name": "Industry",
				"type": "varchar"
			},
			{
				"name": "Symbol",
				"type": "varchar"
			},
			{
				"name": "Series",
				"type": "varchar"
			},
			{
				"name": "ISIN",
				"type": "varchar"
			},
			{
				"name": "Type",
				"type": "varchar"
			}
		],
		"typeProperties": {
			"schema": "dbo",
			"table": "NIFTY_DETAILS"
		}
	},
	"type": "Microsoft.DataFactory/factories/datasets"
}